stella_workflow/__init__.py
stella_workflow/brokers/__init__.py
stella_workflow/brokers/base.py
stella_workflow/brokers/redis_broker.py
stella_workflow/loop.py
stella_workflow/utils.py
stella_workflow/workflow.py
stella_workflow-0.1.0.dist-info/LICENSE
stella_workflow-0.1.0.dist-info/METADATA
stella_workflow-0.1.0.dist-info/WHEEL
stella_workflow-0.1.0.dist-info/RECORD
