Metadata-Version: 2.3
Name: stella-workflow
Version: 0.1.0
Summary: A workflow engine for AI agents
License: MIT
Keywords: workflow,ai,agents,async,redis
Author: Vinay karode
Author-email: vinaykarode@stellaheystella.com
Requires-Python: >=3.10,<4.0
Classifier: Development Status :: 4 - Beta
Classifier: Intended Audience :: Developers
Classifier: License :: OSI Approved :: MIT License
Classifier: Programming Language :: Python :: 3
Classifier: Programming Language :: Python :: 3.10
Classifier: Programming Language :: Python :: 3.11
Classifier: Programming Language :: Python :: 3.12
Classifier: Programming Language :: Python :: 3.13
Classifier: Topic :: Software Development :: Libraries :: Python Modules
Requires-Dist: matplotlib (>=3.10.0,<4.0.0)
Requires-Dist: networkx (>=3.4.2,<4.0.0)
Requires-Dist: pandas (>=2.2.3,<3.0.0)
Requires-Dist: pydantic (>=2.6.4,<3.0.0)
Requires-Dist: redis (>=5.2.1,<6.0.0)
Project-URL: Documentation, https://github.com/stellaheystella/stella-workflow/docs
Project-URL: Repository, https://github.com/stellaheystella/stella-workflow
